twomartens.calendarsync-1.1.3-py3.6-nspkg.pth
twomartens/calendarsync/__init__.py
twomartens/calendarsync/__main__.py
twomartens/calendarsync/calendarsync.py
twomartens/calendarsync/event_template.markdown
twomartens.calendarsync-1.1.3.dist-info/LICENSE.txt
twomartens.calendarsync-1.1.3.dist-info/METADATA
twomartens.calendarsync-1.1.3.dist-info/WHEEL
twomartens.calendarsync-1.1.3.dist-info/entry_points.txt
twomartens.calendarsync-1.1.3.dist-info/namespace_packages.txt
twomartens.calendarsync-1.1.3.dist-info/top_level.txt
twomartens.calendarsync-1.1.3.dist-info/RECORD
