Metadata-Version: 2.1
Name: twomartens.calendarsync
Version: 1.1.3
Summary: Tool that synchronizes Jekyll event collection with remote calendar
Home-page: https://git.2martens.de/2martens/calendar-synchronization
Author: Jim Martens
Author-email: github@2martens.de
License: Apache License 2.0
Platform: UNKNOWN
Classifier: Operating System :: OS Independent
Classifier: Development Status :: 5 - Production/Stable
Classifier: License :: OSI Approved :: Apache Software License
Classifier: Environment :: Console
Classifier: Topic :: Utilities
Classifier: Programming Language :: Python
Classifier: Programming Language :: Python :: 3
Classifier: Programming Language :: Python :: 3.6
Classifier: Programming Language :: Python :: 3.7
Requires-Python: ~=3.6
Requires-Dist: ics (>=0.4)
